flipanimgen/__init__.py
flipanimgen/__main__.py
flipanimgen/cli.py
flipanimgen/dithering.py
flipanimgen/main.py
flipanimgen/metadata.py
flipanimgen/ofw.py
flipanimgen-1.0.0.dist-info/LICENSE
flipanimgen-1.0.0.dist-info/METADATA
flipanimgen-1.0.0.dist-info/WHEEL
flipanimgen-1.0.0.dist-info/entry_points.txt
flipanimgen-1.0.0.dist-info/RECORD
