Metadata-Version: 2.1
Name: flipanimgen
Version: 1.0.0
Summary: Dithering animation generator from video files for Flipper Zero written in Python
License: MIT
Author: D4n13l3k00
Author-email: D4n13l3k00@yandex.ru
Requires-Python: >=3.10,<4.0
Classifier: License :: OSI Approved :: MIT License
Classifier: Programming Language :: Python :: 3
Classifier: Programming Language :: Python :: 3.10
Classifier: Programming Language :: Python :: 3.11
Classifier: Programming Language :: Python :: 3.12
Requires-Dist: numba (>=0.60.0,<0.61.0)
Requires-Dist: numpy (>=2.0.1,<3.0.0)
Requires-Dist: opencv-python (>=4.10.0.84,<5.0.0.0)
Requires-Dist: rich (>=13.7.1,<14.0.0)
